{
  "best_metric": 0.6122223734855652,
  "best_model_checkpoint": "checkpoint/speaker-segmentation-fine-tuned-callhome-jpn/checkpoint-336",
  "epoch": 1.0,
  "eval_steps": 500,
  "global_step": 336,
  "is_hyper_param_search": false,
  "is_local_process_zero": true,
  "is_world_process_zero": true,
  "log_history": [
    {
      "epoch": 0.6,
      "grad_norm": 1.305570363998413,
      "learning_rate": 0.0004047619047619048,
      "loss": 0.6365,
      "step": 200
    },
    {
      "epoch": 1.0,
      "eval_confusion": 0.0512264221906662,
      "eval_der": 0.20516923069953918,
      "eval_false_alarm": 0.08004748076200485,
      "eval_loss": 0.6122223734855652,
      "eval_missed_detection": 0.07389533519744873,
      "eval_runtime": 8.2792,
      "eval_samples_per_second": 83.946,
      "eval_steps_per_second": 2.657,
      "step": 336
    }
  ],
  "logging_steps": 200,
  "max_steps": 336,
  "num_input_tokens_seen": 0,
  "num_train_epochs": 1,
  "save_steps": 500,
  "total_flos": 0.0,
  "train_batch_size": 32,
  "trial_name": null,
  "trial_params": null
}
